parcel_tw/__init__.py
parcel_tw/base.py
parcel_tw/core.py
parcel_tw/enums.py
parcel_tw/family_mart.py
parcel_tw/okmart.py
parcel_tw/seven_eleven.py
parcel_tw/shopee.py
parcel_tw-0.0.1.dist-info/METADATA
parcel_tw-0.0.1.dist-info/WHEEL
parcel_tw-0.0.1.dist-info/licenses/LICENSE
parcel_tw-0.0.1.dist-info/RECORD
