Metadata-Version: 2.4
Name: parcel_tw
Version: 0.0.1
Summary: The Python package for Taiwan parcel tracking.
Project-URL: Homepage, https://github.com/ryanycs/parcel_tw
Project-URL: Issues, https://github.com/ryanycs/parcel_tw/issues
Author: ryanycs
License-File: LICENSE
Classifier: License :: OSI Approved :: MIT License
Classifier: Operating System :: OS Independent
Classifier: Programming Language :: Python :: 3.10
Classifier: Programming Language :: Python :: 3.11
Classifier: Programming Language :: Python :: 3.12
Requires-Python: >=3.10
Requires-Dist: beautifulsoup4
Requires-Dist: pillow
Requires-Dist: pytesseract
Requires-Dist: requests
